qweatherpyapi/__init__.py
qweatherpyapi/geo_model.py
qweatherpyapi/http_request_manager.py
qweatherpyapi/model.py
qweatherpyapi/qweather.py
qweatherPyAPI-0.1.4.dist-info/LICENSE
qweatherPyAPI-0.1.4.dist-info/METADATA
qweatherPyAPI-0.1.4.dist-info/WHEEL
qweatherPyAPI-0.1.4.dist-info/top_level.txt
qweatherPyAPI-0.1.4.dist-info/RECORD
